{
  "basics": {
    "name": "Yong-Jun Shin",
    "label": "Researcher (Software engineering)",
    "image": "",
    "email": "yjshin@etri.re.kr",
    "phone": "(+82) 42-860-3815",
    "url": "https://yongjunshin.github.io/",
    "summary": "Software engineering researcher of ETRI, South Korea",
    "location": {
      "address": "401, Building#7, ETRI, Daejeon, South Korea",
      "postalCode": "34129",
      "city": "Daejeon",
      "countryCode": "KR",
      "region": ""
    },
    "profiles": [
      {
        "network": "",
        "username": "",
        "url": ""
      }
    ]
  },
  "work": [
    {
      "name": "Electronics and Telecommunications Research Institute (ETRI), South Korea",
      "location": "Daejeon, South Korea",
      "position": "Researcher",
      "url": "https://www.etri.re.kr/eng/main/main.etri",
      "startDate": "2023-01-01",
      "endDate": "",
      "summary": "Software engineering for AI-based autonomous systems on edge computing"
    }
  ],
  "education": [
    {
      "institution": "Korea Advanced Institute of Science and Technology (KAIST)",
      "location": "Daejeon, South Korea",
      "url": "https://www.kaist.ac.kr/en/",
      "area": "Software Engineering, School of Computing",
      "studyType": "PhD",
      "startDate": "2017-03-01",
      "endDate": "2023-02-28",
      "summary": "Model-based software engineering for system-of-systems and cyber-physical systems.\nThesis: Data-Driven Environment Model Generation Using Imitation Learning For Efficient Cyber-Physical System Goal Verification"
    },
    {
      "institution": "Handong Global University",
      "location": "Pohang, South Korea",
      "url": "",
      "area": "School of Computer Science and Electrical Engineering",
      "studyType": "BS",
      "startDate": "2013-03-01",
      "endDate": "2017-02-28"
    }
  ],
  "awards": [
    {
      "title": "Best Artifact Paper Award",
      "date": "2021",
      "awarder": "16th Symposium on Software Engineering for Adaptive and Self-Managing Systems (SEAMS)",
      "summary": "Platooning LEGOs: An Open Physical Exemplar for Engineering Self-Adaptive Cyber-Physical Systems-of-Systems"
    },
    {
      "title": "Best Paper Award",
      "date": "2019",
      "awarder": "Korea Computer Congress (KCC)",
      "summary": "Analysis of Utilization Methods of Statistical Model Checking Results for Localizing Faults on System of Systems (시스템 오브 시스템즈의 오류 위치 추정을 위한 통계적 검증 결과 활용 기법 분석)"
    },
    {
      "title": "Outstanding Paper Award",
      "date": "2018",
      "awarder": "Korea Software Congress (KSC)",
      "summary": "Data-Driven Traffic Environment System-Dynamics Model Generation & Inference Method (데이터 기반 교통 흐름 시스템 다이내믹스 환경 모델 생성 및 추론 기법)"
    },
    {
      "title": "Best Paper Award",
      "date": "2018",
      "awarder": "20th Korea Conference on Software Engineering (KCSE)",
      "summary": "Scenario-based Analysis of System-of-Systems Meta-model and Applicability Analysis for Statistical Verification (시스템 오브 시스템즈(SoS) 사례 분석을 통한 온톨로지 기반의 SoS 메타모델 개발)"
    }
  ],
  "volunteer": [
    {
      "organization": "The 12th ACM/IEEE International Workshop on Software Engineering for Systems-of-Systems and Software Ecosystems (SESoS)",
      "position": "Program Committee",
      "date": "2024",
      "summary": "Paper review"
    },
    {
      "organization": "The 36th International Conference on Software Engineering & Knowledge Engineering (SEKE)",
      "position": "Program Committee",
      "date": "2024",
      "summary": "Paper review"
    },
    {
      "organization": "Journal of Software: Evolution and Process - special issue on 'Software Engineering for Systems-of-Systems and Software Ecosystems'",
      "position": "Reviewer",
      "date": "2023",
      "summary": "Paper review"
    },
    {
      "organization": "The 42th International Conference on Software Engineering (ICSE)",
      "position": "Live! Team Korea",
      "date": "2020",
      "summary": "Conference virtualization"
    }
  ]
}
